authsch/__init__.py
authsch/apps.py
authsch/models.py
authsch/views.py
django_authsch-0.7.dist-info/DESCRIPTION.rst
django_authsch-0.7.dist-info/METADATA
django_authsch-0.7.dist-info/RECORD
django_authsch-0.7.dist-info/WHEEL
django_authsch-0.7.dist-info/metadata.json
django_authsch-0.7.dist-info/top_level.txt
